home/lighthouse/lib/libopenblas.so
numpy/__config__.py
numpy/__config__.pyi
numpy/__init__.cython-30.pxd
numpy/__init__.pxd
numpy/__init__.py
numpy/__init__.pyi
numpy/_array_api_info.py
numpy/_array_api_info.pyi
numpy/_configtool.py
numpy/_configtool.pyi
numpy/_distributor_init.py
numpy/_distributor_init.pyi
numpy/_expired_attrs_2_0.py
numpy/_expired_attrs_2_0.pyi
numpy/_globals.py
numpy/_globals.pyi
numpy/_pytesttester.py
numpy/_pytesttester.pyi
numpy/conftest.py
numpy/ctypeslib.py
numpy/ctypeslib.pyi
numpy/dtypes.py
numpy/dtypes.pyi
numpy/exceptions.py
numpy/exceptions.pyi
numpy/matlib.py
numpy/matlib.pyi
numpy/py.typed
numpy/version.py
numpy/version.pyi
numpy/_core/__init__.py
numpy/_core/__init__.pyi
numpy/_core/_add_newdocs.py
numpy/_core/_add_newdocs_scalars.py
numpy/_core/_asarray.py
numpy/_core/_asarray.pyi
numpy/_core/_dtype.py
numpy/_core/_dtype_ctypes.py
numpy/_core/_exceptions.py
numpy/_core/_internal.py
numpy/_core/_internal.pyi
numpy/_core/_machar.py
numpy/_core/_methods.py
numpy/_core/_multiarray_tests.cpython-312.so
numpy/_core/_multiarray_umath.cpython-312.so
numpy/_core/_operand_flag_tests.cpython-312.so
numpy/_core/_rational_tests.cpython-312.so
numpy/_core/_simd.cpython-312.so
numpy/_core/_string_helpers.py
numpy/_core/_struct_ufunc_tests.cpython-312.so
numpy/_core/_type_aliases.py
numpy/_core/_type_aliases.pyi
numpy/_core/_ufunc_config.py
numpy/_core/_ufunc_config.pyi
numpy/_core/_umath_tests.cpython-312.so
numpy/_core/arrayprint.py
numpy/_core/arrayprint.pyi
numpy/_core/cversions.py
numpy/_core/defchararray.py
numpy/_core/defchararray.pyi
numpy/_core/einsumfunc.py
numpy/_core/einsumfunc.pyi
numpy/_core/fromnumeric.py
numpy/_core/fromnumeric.pyi
numpy/_core/function_base.py
numpy/_core/function_base.pyi
numpy/_core/getlimits.py
numpy/_core/getlimits.pyi
numpy/_core/memmap.py
numpy/_core/memmap.pyi
numpy/_core/multiarray.py
numpy/_core/multiarray.pyi
numpy/_core/numeric.py
numpy/_core/numeric.pyi
numpy/_core/numerictypes.py
numpy_aipy-2.2.3.1.dist-info/METADATA
numpy_aipy-2.2.3.1.dist-info/WHEEL
numpy_aipy-2.2.3.1.dist-info/top_level.txt
numpy_aipy-2.2.3.1.dist-info/RECORD
