Metadata-Version: 2.4
Name: numpy-aipy
Version: 2.2.3.1
Summary: The fundamental package needed for scientific computing with Python
Home-page: https://qpypi.qpython.org/project/numpy-aipy/
Author: The QPYPI Team
Author-email: qpypi@qpython.org
License: MIT AND (Apache-2.0 OR BSD-2-Clause)
Classifier: Intended Audience :: Developers
Classifier: Intended Audience :: Education
Classifier: Intended Audience :: Information Technology
Classifier: Intended Audience :: End Users/Desktop
Classifier: License :: OSI Approved :: Apache Software License
Classifier: Operating System :: Android
Classifier: Programming Language :: Python
Classifier: Programming Language :: Python :: 3.12
Classifier: Topic :: Software Development
Dynamic: author
Dynamic: author-email
Dynamic: classifier
Dynamic: description
Dynamic: home-page
Dynamic: license
Dynamic: summary
